analyzer/__init__.py
analyzer/codegen.py
analyzer/convexity_checker.py
analyzer/solvers.py
analyzer/tech_support.py
analyzer/version.py
cvxpyanalyzer-0.0.3.dist-info/LICENSE
cvxpyanalyzer-0.0.3.dist-info/METADATA
cvxpyanalyzer-0.0.3.dist-info/WHEEL
cvxpyanalyzer-0.0.3.dist-info/top_level.txt
cvxpyanalyzer-0.0.3.dist-info/RECORD
